{
  "logserver" : {
    "token" : {
      "key" : "84A3A78B42D6018F0C7995C6802DDB550E38163288DAB13FCE130E568EAB576899993C0D3E1E2F4627A18EF2CB8492249E983041B3628FEDD9822A0E59B31E40",
      "expiry" : 1479189657,
      "domain" : "logging.node@server.1"
    },
    "system" : "logging.node",
    "host" : "server.1"
  },
  "elastic" : {
    "remote" : "localhost",
    "index" : "chili.core.logging.v101",
    "port" : 9200,
    "template" : {
      "mappings" : {
        "the_def_index" : {
          "properties" : {
            "time" : {
              "type" : "date"
            }
          }
        }
      }
    },
    "enabled" : true
  },
  "secret" : "0IlQn5igqPg/4/8mwe64SeSrAPCKHIHKGLHFpyBuYvzNIMZ3u5xwQ3mohy+SXzEZIFRwey7BZ0uhbfo29lD73w==",
  "console" : true
}