{
  "attributes" : {
    "drop" : 1.0,
    "classes" : [ "Paladin" ],
    "description" : "Stable realm, PvP Aggressive.",
    "leveling" : 1.0
  },
  "authentication" : {
    "token" : {
      "key" : "0AB719D99183BA6CFCB3D599F2568E0A95A0B0081BC41B8981CF5281A49242D1648D8E187E4C1278EA72D2F0946EEFACF090F739067FC8E2A90D0832DD9D58BB",
      "expiry" : 1479311512,
      "domain" : "Angel Oak"
    }
  },
  "name" : "Angel Oak",
  "resources" : "patching.node",
  "version" : 1.0,
  "size" : 5000,
  "type" : "PvP",
  "lifetime" : "weekly",
  "players" : 0,
  "remote" : "Angel Oak.realm.node"
}